phis_lifestyle_advice/__init__.py
phis_lifestyle_advice/__main__.py
phis_lifestyle_advice-2025.7.23.7.dist-info/METADATA
phis_lifestyle_advice-2025.7.23.7.dist-info/WHEEL
phis_lifestyle_advice-2025.7.23.7.dist-info/licenses/LICENSE
phis_lifestyle_advice-2025.7.23.7.dist-info/RECORD
