Metadata-Version: 2.4
Name: phis-lifestyle-advice
Version: 2025.7.23.7
Summary: 慢病随访新建-生活建议
License-File: LICENSE
Requires-Python: >=3.12
